{
  "fileName": "yagsl-2026.1.24.json",
  "name": "YAGSL",
  "version": "2026.1.24",
  "frcYear": "2026",
  "uuid": "1ccce5a4-acd2-4d18-bca3-4b8047188400",
  "mavenUrls": [
    "https://yet-another-software-suite.github.io/YAGSL/releases/",
	"https://repo1.maven.org/maven2"
  ],
  "jsonUrl": "https://yet-another-software-suite.github.io/YAGSL/yagsl.json",
  "javaDependencies": [
    {
      "groupId": "swervelib",
      "artifactId": "YAGSL-java",
      "version": "2026.1.24"
    },
	{
            "groupId": "org.dyn4j",
            "artifactId": "dyn4j",
            "version": "5.0.2"
	}
  ],
  "requires": [
    {
      "uuid": "151ecca8-670b-4026-8160-cdd2679ef2bd",
      "errorMessage": "ReduxLib is required!",
      "offlineFileName": "ReduxLib.json",
      "onlineUrl": "https://frcsdk.reduxrobotics.com/ReduxLib_2026.json"
    },
    {
      "uuid": "3f48eb8c-50fe-43a6-9cb7-44c86353c4cb",
      "errorMessage": "REVLib is required!",
      "offlineFileName": "REVLib.json",
      "onlineUrl": "https://software-metadata.revrobotics.com/REVLib-2026.json"
    },
    {
      "uuid": "e7900d8d-826f-4dca-a1ff-182f658e98af",
      "errorMessage": "Phoenix6 Replay is required!",
      "offlineFileName": "Phoenix6-replay-26.1.0.json",
      "onlineUrl": "https://maven.ctr-electronics.com/release/com/ctre/phoenix6/latest/Phoenix6-replay-frc2026-latest.json"
    },
    {
      "uuid": "fbc886a4-2cec-40c0-9835-71086a8cc3df",
      "errorMessage": "Phoenix5 Replay Compatibility is required!",
      "offlineFileName": "Phoenix5-replay-5.36.0.json",
      "onlineUrl": "https://maven.ctr-electronics.com/release/com/ctre/phoenix/Phoenix5-replay-frc2026-latest.json"
    },
    {
      "uuid": "60b2694b-9e6e-4026-81ee-6f167946f4b0",
      "errorMessage": "ThriftyLib is required!",
      "offlineFileName": "ThriftyLib.json",
      "onlineUrl": "https://docs.home.thethriftybot.com/ThriftyLib-2026.json"
    }
  ],
  "jniDependencies": [],
  "cppDependencies": []
}
